token_throttle/__init__.py
token_throttle/_rate_limiter.py
token_throttle/_factories/__init__.py
token_throttle/_factories/_openai/__init__.py
token_throttle/_factories/_openai/_openai_rate_limiter.py
token_throttle/_factories/_openai/_token_counter.py
token_throttle/_interfaces/__init__.py
token_throttle/_interfaces/_callbacks.py
token_throttle/_interfaces/_interfaces.py
token_throttle/_interfaces/_models.py
token_throttle/_limiter_backends/__init__.py
token_throttle/_limiter_backends/_redis/__init__.py
token_throttle/_limiter_backends/_redis/_backend.py
token_throttle/_limiter_backends/_redis/_bucket.py
token_throttle-0.4.2.dist-info/METADATA
token_throttle-0.4.2.dist-info/WHEEL
token_throttle-0.4.2.dist-info/licenses/LICENSE
token_throttle-0.4.2.dist-info/RECORD
