Metadata-Version: 2.4
Name: token-throttle
Version: 0.4.2
Summary: Simple Multi-Resource Rate Limiting That Saves Unused Tokens. Rate limit API requests across different resources and workers without wasting your quota. Reserve tokens upfront, get refunds for what you don't use, and avoid over-limiting.
License-File: LICENSE
Requires-Python: >=3.12
Requires-Dist: frozendict>=2.4.6
Requires-Dist: pydantic>=2.11.3
Provides-Extra: redis
Requires-Dist: redis>=5.2.1; extra == 'redis'
Provides-Extra: tiktoken
Requires-Dist: tiktoken>=0.4.0; extra == 'tiktoken'
